uulm_mensa/__init__.py
uulm_mensa/cli.py
uulm_mensa-0.1.0.dist-info/DESCRIPTION.rst
uulm_mensa-0.1.0.dist-info/METADATA
uulm_mensa-0.1.0.dist-info/RECORD
uulm_mensa-0.1.0.dist-info/WHEEL
uulm_mensa-0.1.0.dist-info/entry_points.txt
uulm_mensa-0.1.0.dist-info/metadata.json
uulm_mensa-0.1.0.dist-info/top_level.txt
