Metadata-Version: 2.0
Name: uulm-mensa
Version: 0.1.0
Summary: Mensa plans for the university ulm
Home-page: https://github.com/mmk2410/uulm-mensa
Author: mmk2410
Author-email: marcelmichaelkapfer@yahoo.co.nz
License: MIT
Keywords: mensa plan bistro uulm ulm
Platform: any
Classifier: Development Status :: 5 - Production/Stable
Classifier: Operating System :: OS Independent
Classifier: Environment :: Console
Classifier: License :: OSI Approved :: MIT License
Classifier: Intended Audience :: End Users/Desktop
Classifier: Topic :: Utilities
Classifier: Programming Language :: Python
Classifier: Programming Language :: Python :: 3
Classifier: Programming Language :: Python :: 3.2
Classifier: Programming Language :: Python :: 3.3
Classifier: Programming Language :: Python :: 3.4
Classifier: Programming Language :: Python :: 3.5
Requires-Dist: datetime
